pursuitlib_django/__init__.py
pursuitlib_django/admin.py
pursuitlib_django/apps.py
pursuitlib_django/decorators.py
pursuitlib_django/email.py
pursuitlib_django/errors.py
pursuitlib_django/forms.py
pursuitlib_django/gravatar.py
pursuitlib_django/models.py
pursuitlib_django/pagination.py
pursuitlib_django/signals.py
pursuitlib_django/tests.py
pursuitlib_django/utils.py
pursuitlib_django/views.py
pursuitlib_django/widgets.py
pursuitlib_django/api/__init__.py
pursuitlib_django/api/decorators.py
pursuitlib_django/api/utils.py
pursuitlib_django/locale/fr/LC_MESSAGES/django.po
pursuitlib_django/migrations/__init__.py
pursuitlib_django/static/css/fa.min.css
pursuitlib_django/static/css/pursuitlib-admin.css
pursuitlib_django/static/css/pursuitlib.css
pursuitlib_django/static/css/select2.min.css
pursuitlib_django/static/js/bootstrap.bundle.min.js
pursuitlib_django/static/js/bootstrap.bundle.min.js.map
pursuitlib_django/static/js/jquery-3.6.0.min.js
pursuitlib_django/static/js/pursuitlib.js
pursuitlib_django/static/js/select2.full.min.js
pursuitlib_django/static/js/i18n/select2/fr.js
pursuitlib_django/static/webfonts/fa-brands-400.eot
pursuitlib_django/static/webfonts/fa-brands-400.svg
pursuitlib_django/static/webfonts/fa-brands-400.ttf
pursuitlib_django/static/webfonts/fa-brands-400.woff
pursuitlib_django/static/webfonts/fa-brands-400.woff2
pursuitlib_django/static/webfonts/fa-regular-400.eot
pursuitlib_django/static/webfonts/fa-regular-400.svg
pursuitlib_django/static/webfonts/fa-regular-400.ttf
pursuitlib_django/static/webfonts/fa-regular-400.woff
pursuitlib_django/static/webfonts/fa-regular-400.woff2
pursuitlib_django/static/webfonts/fa-solid-900.eot
pursuitlib_django/static/webfonts/fa-solid-900.svg
pursuitlib_django/static/webfonts/fa-solid-900.ttf
pursuitlib_django/static/webfonts/fa-solid-900.woff
pursuitlib_django/static/webfonts/fa-solid-900.woff2
pursuitlib_django/templates/pursuitlib/component/form-field.html
pursuitlib_django-0.3.2.dist-info/METADATA
pursuitlib_django-0.3.2.dist-info/WHEEL
pursuitlib_django-0.3.2.dist-info/top_level.txt
pursuitlib_django-0.3.2.dist-info/RECORD
