Metadata-Version: 2.1
Name: pursuitlib-django
Version: 0.3.2
Summary: Provides utility functions for Django
Home-page: https://gitlab.com/frPursuit/pursuitlib-python
Author: Pursuit
Author-email: fr.pursuit@gmail.com
License: All rights reserved
Classifier: Programming Language :: Python :: 3
Classifier: Operating System :: OS Independent
Requires-Python: >=3.8
Requires-Dist: pursuitlib
Requires-Dist: Django
Requires-Dist: django-select2
